dataclassframe/__init__.py
dataclassframe/dataclassframe_.py
dataclassframe/test_dataclassframe.py
dataclassframe-0.1.0.dist-info/LICENSE
dataclassframe-0.1.0.dist-info/METADATA
dataclassframe-0.1.0.dist-info/WHEEL
dataclassframe-0.1.0.dist-info/top_level.txt
dataclassframe-0.1.0.dist-info/RECORD
