Metadata-Version: 2.1
Name: dataclassframe
Version: 0.1.0
Summary: A dataclass container with multi-indexing and bulk operations
Home-page: https://github.com/joshlk/dataclassframe
Author: Josh Levy-Kramer
License: MIT License
Project-URL: Documentation, https://joshlk.github.io/dataclassframe
Project-URL: Code, https://github.com/joshlk/dataclassframe
Project-URL: Issue tracker, https://github.com/joshlk/dataclassframe/issues
Platform: UNKNOWN
Classifier: Development Status :: 5 - Production/Stable
Classifier: Intended Audience :: Developers
Classifier: Topic :: Utilities
Classifier: License :: OSI Approved :: MIT License
Classifier: Programming Language :: Python :: 3
Requires-Python: >=3.6
Requires-Dist: pandas
Requires-Dist: dataclasses ; python_version < "3.7"
Provides-Extra: dev
Requires-Dist: pytest ; extra == 'dev'
Requires-Dist: wheel ; extra == 'dev'
Requires-Dist: setuptools ; extra == 'dev'
Requires-Dist: twine ; extra == 'dev'
Requires-Dist: sphinx (>=3.2.1) ; extra == 'dev'
Requires-Dist: codecov ; extra == 'dev'
Requires-Dist: recommonmark ; extra == 'dev'
Requires-Dist: sphinx-rtd-theme ; extra == 'dev'
Requires-Dist: bump2version ; extra == 'dev'
Provides-Extra: docs
Requires-Dist: sphinx ; extra == 'docs'
Requires-Dist: sphinx-rtd-theme ; extra == 'docs'
